dill/__diff.py
dill/__info__.py
dill/__init__.py
dill/_dill.py
dill/_objects.py
dill/_shims.py
dill/detect.py
dill/logger.py
dill/objtypes.py
dill/pointers.py
dill/session.py
dill/settings.py
dill/source.py
dill/temp.py
dill/tests/__init__.py
dill/tests/__main__.py
dill/tests/test_check.py
dill/tests/test_classdef.py
dill/tests/test_dataclasses.py
dill/tests/test_detect.py
dill/tests/test_dictviews.py
dill/tests/test_diff.py
dill/tests/test_extendpickle.py
dill/tests/test_fglobals.py
dill/tests/test_file.py
dill/tests/test_functions.py
dill/tests/test_functors.py
dill/tests/test_logger.py
dill/tests/test_mixins.py
dill/tests/test_module.py
dill/tests/test_moduledict.py
dill/tests/test_nested.py
dill/tests/test_objects.py
dill/tests/test_properties.py
dill/tests/test_pycapsule.py
dill/tests/test_recursive.py
dill/tests/test_registered.py
dill/tests/test_restricted.py
dill/tests/test_selected.py
dill/tests/test_session.py
dill/tests/test_source.py
dill/tests/test_temp.py
dill/tests/test_weakref.py
dill_pylint-0.3.6.data/scripts/get_objgraph
dill_pylint-0.3.6.data/scripts/undill
dill_pylint-0.3.6.dev0.dist-info/LICENSE
dill_pylint-0.3.6.dev0.dist-info/METADATA
dill_pylint-0.3.6.dev0.dist-info/WHEEL
dill_pylint-0.3.6.dev0.dist-info/top_level.txt
dill_pylint-0.3.6.dev0.dist-info/RECORD
