Metadata-Version: 2.1
Name: dill-pylint
Version: 0.3.6.dev0
Summary: serialize all of python
Home-page: https://github.com/uqfoundation/dill
Download-URL: https://pypi.org/project/dill/#files
Author: Mike McKerns
Author-email: mmckerns@uqfoundation.org
Maintainer: Mike McKerns
Maintainer-email: mmckerns@uqfoundation.org
License: BSD-3-Clause
Project-URL: Documentation, http://dill.rtfd.io
Project-URL: Source Code, https://github.com/uqfoundation/dill
Project-URL: Bug Tracker, https://github.com/uqfoundation/dill/issues
Platform: Linux
Platform: Windows
Platform: Mac
Classifier: Development Status :: 5 - Production/Stable
Classifier: Intended Audience :: Developers
Classifier: Intended Audience :: Science/Research
Classifier: License :: OSI Approved :: BSD License
Classifier: Programming Language :: Python :: 3
Classifier: Programming Language :: Python :: 3.7
Classifier: Programming Language :: Python :: 3.8
Classifier: Programming Language :: Python :: 3.9
Classifier: Programming Language :: Python :: 3.10
Classifier: Programming Language :: Python :: Implementation :: CPython
Classifier: Programming Language :: Python :: Implementation :: PyPy
Classifier: Topic :: Scientific/Engineering
Classifier: Topic :: Software Development
Requires-Python: >=3.7
License-File: LICENSE
Provides-Extra: graph
Requires-Dist: objgraph (>=1.7.2) ; extra == 'graph'
Provides-Extra: readline
